Workbook

Sheet Nightshift 12-month assumed out
A1: Nightshift 12-month assumed outcomes
A2: Nightshift — Scenario comparison · Main Scenario
A4: Variable / dimension | B4: Value | C4: Value > Higher price | D4: Value > delta
A5: 12-month assumed revenue | B5: =SUM('Model inputs'!L8,'Model inputs'!M8,'Model inputs'!N8,'Model inputs'!O8,'Model inputs'!P8,'Model inputs'!Q8,'Model inputs'!R8,'Model inputs'!S8,'Model inputs'!T8,'Model inputs'!U8,'Model inputs'!V8,'Model inputs'!W8) -> 10780 | C5: =SUM('Model inputs'!L9,'Model inputs'!M9,'Model inputs'!N9,'Model inputs'!O9,'Model inputs'!P9,'Model inputs'!Q9,'Model inputs'!R9,'Model inputs'!S9,'Model inputs'!T9,'Model inputs'!U9,'Model inputs'!V9,'Model inputs'!W9) -> 17380 | D5: ='Nightshift 12-month assumed out'!C5-'Nightshift 12-month assumed out'!B5 -> 6600
A6: 12-month assumed total cost | B6: =SUM('Model inputs'!L10,'Model inputs'!M10,'Model inputs'!N10,'Model inputs'!O10,'Model inputs'!P10,'Model inputs'!Q10,'Model inputs'!R10,'Model inputs'!S10,'Model inputs'!T10,'Model inputs'!U10,'Model inputs'!V10,'Model inputs'!W10) -> 333 | C6: =SUM('Model inputs'!L11,'Model inputs'!M11,'Model inputs'!N11,'Model inputs'!O11,'Model inputs'!P11,'Model inputs'!Q11,'Model inputs'!R11,'Model inputs'!S11,'Model inputs'!T11,'Model inputs'!U11,'Model inputs'!V11,'Model inputs'!W11) -> 333 | D6: ='Nightshift 12-month assumed out'!C6-'Nightshift 12-month assumed out'!B6 -> 0
A7: Horizon assumed ending cash | B7: =IF('Model inputs'!W6="","",'Model inputs'!W6) -> 10447 | C7: =IF('Model inputs'!W7="","",'Model inputs'!W7) -> 17047 | D7: ='Nightshift 12-month assumed out'!C7-'Nightshift 12-month assumed out'!B7 -> 6600
A8: Assumed runway months | B8: =IF(IF(IF(ISERROR(MIN('Model inputs'!L6,'Model inputs'!M6,'Model inputs'!N6,'Model inputs'!O6,'Model inputs'!P6,'Model inputs'!Q6,'Model inputs'!R6,'Model inputs'!S6,'Model inputs'!T6,'Model inputs'!U6,'Model inputs'!V6,'Model inputs'!W6)>=0),MIN('Model inputs'!L6,'Model inputs'!M6,'Model inputs'!N6,'Model inputs'!O6,'Model inputs'!P6,'Model inputs'!Q6,'Model inputs'!R6,'Model inputs'!S6,'Model inputs'!T6,'Model inputs'!U6,'Model inputs'!V6,'Model inputs'!W6)>=0,IF(MIN('Model inputs'!L6,'Model inputs'!M6,'Model inputs'!N6,'Model inputs'!O6,'Model inputs'!P6,'Model inputs'!Q6,'Model inputs'!R6,'Model inputs'!S6,'Model inputs'!T6,'Model inputs'!U6,'Model inputs'!V6,'Model inputs'!W6)="","",MIN('Model inputs'!L6,'Model inputs'!M6,'Model inputs'!N6,'Model inputs'!O6,'Model inputs'!P6,'Model inputs'!Q6,'Model inputs'!R6,'Model inputs'!S6,'Model inputs'!T6,'Model inputs'!U6,'Model inputs'!V6,'Model inputs'!W6)>=0))="",FALSE,IF(ISERROR(MIN('Model inputs'!L6,'Model inputs'!M6,'Model inputs'!N6,'Model inputs'!O6,'Model inputs'!P6,'Model inputs'!Q6,'Model inputs'!R6,'Model inputs'!S6,'Model inputs'!T6,'Model inputs'!U6,'Model inputs'!V6,'Model inputs'!W6)>=0),MIN('Model inputs'!L6,'Model inputs'!M6,'Model inputs'!N6,'Model inputs'!O6,'Model inputs'!P6,'Model inputs'!Q6,'Model inputs'!R6,'Model inputs'!S6,'Model inputs'!T6,'Model inputs'!U6,'Model inputs'!V6,'Model inputs'!W6)>=0,IF(MIN('Model inputs'!L6,'Model inputs'!M6,'Model inputs'!N6,'Model inputs'!O6,'Model inputs'!P6,'Model inputs'!Q6,'Model inputs'!R6,'Model inputs'!S6,'Model inputs'!T6,'Model inputs'!U6,'Model inputs'!V6,'Model inputs'!W6)="","",MIN('Model inputs'!L6,'Model inputs'!M6,'Model inputs'!N6,'Model inputs'!O6,'Model inputs'!P6,'Model inputs'!Q6,'Model inputs'!R6,'Model inputs'!S6,'Model inputs'!T6,'Model inputs'!U6,'Model inputs'!V6,'Model inputs'!W6)>=0))),"",IF(IF(IF(ISERROR('Model inputs'!L6<0),'Model inputs'!L6<0,IF('Model inputs'!L6="","",'Model inputs'!L6<0))="",FALSE,IF(ISERROR('Model inputs'!L6<0),'Model inputs'!L6<0,IF('Model inputs'!L6="","",'Model inputs'!L6<0))),0,IF(IF(IF(ISERROR('Model inputs'!M6<0),'Model inputs'!M6<0,IF('Model inputs'!M6="","",'Model inputs'!M6<0))="",FALSE,IF(ISERROR('Model inputs'!M6<0),'Model inputs'!M6<0,IF('Model inputs'!M6="","",'Model inputs'!M6<0))),1,IF(IF(IF(ISERROR('Model inputs'!N6<0),'Model inputs'!N6<0,IF('Model inputs'!N6="","",'Model inputs'!N6<0))="",FALSE,IF(ISERROR('Model inputs'!N6<0),'Model inputs'!N6<0,IF('Model inputs'!N6="","",'Model inputs'!N6<0))),2,IF(IF(IF(ISERROR('Model inputs'!O6<0),'Model inputs'!O6<0,IF('Model inputs'!O6="","",'Model inputs'!O6<0))="",FALSE,IF(ISERROR('Model inputs'!O6<0),'Model inputs'!O6<0,IF('Model inputs'!O6="","",'Model inputs'!O6<0))),3,IF(IF(IF(ISERROR('Model inputs'!P6<0),'Model inputs'!P6<0,IF('Model inputs'!P6="","",'Model inputs'!P6<0))="",FALSE,IF(ISERROR('Model inputs'!P6<0),'Model inputs'!P6<0,IF('Model inputs'!P6="","",'Model inputs'!P6<0))),4,IF(IF(IF(ISERROR('Model inputs'!Q6<0),'Model inputs'!Q6<0,IF('Model inputs'!Q6="","",'Model inputs'!Q6<0))="",FALSE,IF(ISERROR('Model inputs'!Q6<0),'Model inputs'!Q6<0,IF('Model inputs'!Q6="","",'Model inputs'!Q6<0))),5,IF(IF(IF(ISERROR('Model inputs'!R6<0),'Model inputs'!R6<0,IF('Model inputs'!R6="","",'Model inputs'!R6<0))="",FALSE,IF(ISERROR('Model inputs'!R6<0),'Model inputs'!R6<0,IF('Model inputs'!R6="","",'Model inputs'!R6<0))),6,IF(IF(IF(ISERROR('Model inputs'!S6<0),'Model inputs'!S6<0,IF('Model inputs'!S6="","",'Model inputs'!S6<0))="",FALSE,IF(ISERROR('Model inputs'!S6<0),'Model inputs'!S6<0,IF('Model inputs'!S6="","",'Model inputs'!S6<0))),7,IF(IF(IF(ISERROR('Model inputs'!T6<0),'Model inputs'!T6<0,IF('Model inputs'!T6="","",'Model inputs'!T6<0))="",FALSE,IF(ISERROR('Model inputs'!T6<0),'Model inputs'!T6<0,IF('Model inputs'!T6="","",'Model inputs'!T6<0))),8,IF(IF(IF(ISERROR('Model inputs'!U6<0),'Model inputs'!U6<0,IF('Model inputs'!U6="","",'Model inputs'!U6<0))="",FALSE,IF(ISERROR('Model inputs'!U6<0),'Model inputs'!U6<0,IF('Model inputs'!U6="","",'Model inputs'!U6<0))),9,IF(IF(IF(ISERROR('Model inputs'!V6<0),'Model inputs'!V6<0,IF('Model inputs'!V6="","",'Model inputs'!V6<0))="",FALSE,IF(ISERROR('Model inputs'!V6<0),'Model inputs'!V6<0,IF('Model inputs'!V6="","",'Model inputs'!V6<0))),10,11)))))))))))) -> 0 | C8: =IF(IF(IF(ISERROR(MIN('Model inputs'!L7,'Model inputs'!M7,'Model inputs'!N7,'Model inputs'!O7,'Model inputs'!P7,'Model inputs'!Q7,'Model inputs'!R7,'Model inputs'!S7,'Model inputs'!T7,'Model inputs'!U7,'Model inputs'!V7,'Model inputs'!W7)>=0),MIN('Model inputs'!L7,'Model inputs'!M7,'Model inputs'!N7,'Model inputs'!O7,'Model inputs'!P7,'Model inputs'!Q7,'Model inputs'!R7,'Model inputs'!S7,'Model inputs'!T7,'Model inputs'!U7,'Model inputs'!V7,'Model inputs'!W7)>=0,IF(MIN('Model inputs'!L7,'Model inputs'!M7,'Model inputs'!N7,'Model inputs'!O7,'Model inputs'!P7,'Model inputs'!Q7,'Model inputs'!R7,'Model inputs'!S7,'Model inputs'!T7,'Model inputs'!U7,'Model inputs'!V7,'Model inputs'!W7)="","",MIN('Model inputs'!L7,'Model inputs'!M7,'Model inputs'!N7,'Model inputs'!O7,'Model inputs'!P7,'Model inputs'!Q7,'Model inputs'!R7,'Model inputs'!S7,'Model inputs'!T7,'Model inputs'!U7,'Model inputs'!V7,'Model inputs'!W7)>=0))="",FALSE,IF(ISERROR(MIN('Model inputs'!L7,'Model inputs'!M7,'Model inputs'!N7,'Model inputs'!O7,'Model inputs'!P7,'Model inputs'!Q7,'Model inputs'!R7,'Model inputs'!S7,'Model inputs'!T7,'Model inputs'!U7,'Model inputs'!V7,'Model inputs'!W7)>=0),MIN('Model inputs'!L7,'Model inputs'!M7,'Model inputs'!N7,'Model inputs'!O7,'Model inputs'!P7,'Model inputs'!Q7,'Model inputs'!R7,'Model inputs'!S7,'Model inputs'!T7,'Model inputs'!U7,'Model inputs'!V7,'Model inputs'!W7)>=0,IF(MIN('Model inputs'!L7,'Model inputs'!M7,'Model inputs'!N7,'Model inputs'!O7,'Model inputs'!P7,'Model inputs'!Q7,'Model inputs'!R7,'Model inputs'!S7,'Model inputs'!T7,'Model inputs'!U7,'Model inputs'!V7,'Model inputs'!W7)="","",MIN('Model inputs'!L7,'Model inputs'!M7,'Model inputs'!N7,'Model inputs'!O7,'Model inputs'!P7,'Model inputs'!Q7,'Model inputs'!R7,'Model inputs'!S7,'Model inputs'!T7,'Model inputs'!U7,'Model inputs'!V7,'Model inputs'!W7)>=0))),"",IF(IF(IF(ISERROR('Model inputs'!L7<0),'Model inputs'!L7<0,IF('Model inputs'!L7="","",'Model inputs'!L7<0))="",FALSE,IF(ISERROR('Model inputs'!L7<0),'Model inputs'!L7<0,IF('Model inputs'!L7="","",'Model inputs'!L7<0))),0,IF(IF(IF(ISERROR('Model inputs'!M7<0),'Model inputs'!M7<0,IF('Model inputs'!M7="","",'Model inputs'!M7<0))="",FALSE,IF(ISERROR('Model inputs'!M7<0),'Model inputs'!M7<0,IF('Model inputs'!M7="","",'Model inputs'!M7<0))),1,IF(IF(IF(ISERROR('Model inputs'!N7<0),'Model inputs'!N7<0,IF('Model inputs'!N7="","",'Model inputs'!N7<0))="",FALSE,IF(ISERROR('Model inputs'!N7<0),'Model inputs'!N7<0,IF('Model inputs'!N7="","",'Model inputs'!N7<0))),2,IF(IF(IF(ISERROR('Model inputs'!O7<0),'Model inputs'!O7<0,IF('Model inputs'!O7="","",'Model inputs'!O7<0))="",FALSE,IF(ISERROR('Model inputs'!O7<0),'Model inputs'!O7<0,IF('Model inputs'!O7="","",'Model inputs'!O7<0))),3,IF(IF(IF(ISERROR('Model inputs'!P7<0),'Model inputs'!P7<0,IF('Model inputs'!P7="","",'Model inputs'!P7<0))="",FALSE,IF(ISERROR('Model inputs'!P7<0),'Model inputs'!P7<0,IF('Model inputs'!P7="","",'Model inputs'!P7<0))),4,IF(IF(IF(ISERROR('Model inputs'!Q7<0),'Model inputs'!Q7<0,IF('Model inputs'!Q7="","",'Model inputs'!Q7<0))="",FALSE,IF(ISERROR('Model inputs'!Q7<0),'Model inputs'!Q7<0,IF('Model inputs'!Q7="","",'Model inputs'!Q7<0))),5,IF(IF(IF(ISERROR('Model inputs'!R7<0),'Model inputs'!R7<0,IF('Model inputs'!R7="","",'Model inputs'!R7<0))="",FALSE,IF(ISERROR('Model inputs'!R7<0),'Model inputs'!R7<0,IF('Model inputs'!R7="","",'Model inputs'!R7<0))),6,IF(IF(IF(ISERROR('Model inputs'!S7<0),'Model inputs'!S7<0,IF('Model inputs'!S7="","",'Model inputs'!S7<0))="",FALSE,IF(ISERROR('Model inputs'!S7<0),'Model inputs'!S7<0,IF('Model inputs'!S7="","",'Model inputs'!S7<0))),7,IF(IF(IF(ISERROR('Model inputs'!T7<0),'Model inputs'!T7<0,IF('Model inputs'!T7="","",'Model inputs'!T7<0))="",FALSE,IF(ISERROR('Model inputs'!T7<0),'Model inputs'!T7<0,IF('Model inputs'!T7="","",'Model inputs'!T7<0))),8,IF(IF(IF(ISERROR('Model inputs'!U7<0),'Model inputs'!U7<0,IF('Model inputs'!U7="","",'Model inputs'!U7<0))="",FALSE,IF(ISERROR('Model inputs'!U7<0),'Model inputs'!U7<0,IF('Model inputs'!U7="","",'Model inputs'!U7<0))),9,IF(IF(IF(ISERROR('Model inputs'!V7<0),'Model inputs'!V7<0,IF('Model inputs'!V7="","",'Model inputs'!V7<0))="",FALSE,IF(ISERROR('Model inputs'!V7<0),'Model inputs'!V7<0,IF('Model inputs'!V7="","",'Model inputs'!V7<0))),10,11)))))))))))) -> 0 | D8: ='Nightshift 12-month assumed out'!C8-'Nightshift 12-month assumed out'!B8 -> 0
A9: Assumed runway status | B9: =IF('Nightshift 12-month assumed out'!B8="","Not exhausted inside the 12-month horizon",IF(IF(IF(ISERROR('Nightshift 12-month assumed out'!B8=0),'Nightshift 12-month assumed out'!B8=0,IF('Nightshift 12-month assumed out'!B8="","",'Nightshift 12-month assumed out'!B8=0))="",FALSE,IF(ISERROR('Nightshift 12-month assumed out'!B8=0),'Nightshift 12-month assumed out'!B8=0,IF('Nightshift 12-month assumed out'!B8="","",'Nightshift 12-month assumed out'!B8=0))),"Exhausted in November 2026; November ending cash is negative","Exhausted inside the horizon; runway months counts months before the first negative month")) -> Exhausted in November 2026; November ending cash is negative | C9: =IF('Nightshift 12-month assumed out'!C8="","Not exhausted inside the 12-month horizon",IF(IF(IF(ISERROR('Nightshift 12-month assumed out'!C8=0),'Nightshift 12-month assumed out'!C8=0,IF('Nightshift 12-month assumed out'!C8="","",'Nightshift 12-month assumed out'!C8=0))="",FALSE,IF(ISERROR('Nightshift 12-month assumed out'!C8=0),'Nightshift 12-month assumed out'!C8=0,IF('Nightshift 12-month assumed out'!C8="","",'Nightshift 12-month assumed out'!C8=0))),"Exhausted in November 2026; November ending cash is negative","Exhausted inside the horizon; runway months counts months before the first negative month")) -> Exhausted in November 2026; November ending cash is negative

Sheet Model inputs
A1: Model inputs
A2: Integration values are aggregated snapshots; raw source records are not included.
A4: Variables
A5: Variable / segment | B5: 2026-01 | C5: 2026-02 | D5: 2026-03 | E5: 2026-04 | F5: 2026-05 | G5: 2026-06 | H5: 2026-07 | I5: 2026-08 | J5: 2026-09 | K5: 2026-10 | L5: 2026-11 | M5: 2026-12 | N5: 2027-01 | O5: 2027-02 | P5: 2027-03 | Q5: 2027-04 | R5: 2027-05 | S5: 2027-06 | T5: 2027-07 | U5: 2027-08 | V5: 2027-09 | W5: 2027-10 | X5: 2027-11 | Y5: 2027-12 | Z5: Value
A6: Assumed ending cash · Main Scenario | B6: 0 | C6: 0 | D6: 0 | E6: 0 | F6: 0 | G6: 0 | H6: 0 | I6: 0 | J6: 0 | K6: =IF(IF(DATE(2026,10,1)=DATE(2026,11,1),IF('Model inputs'!Z22="","",'Model inputs'!Z22),IF('Model inputs'!J6="","",'Model inputs'!J6))="",0,IF(DATE(2026,10,1)=DATE(2026,11,1),IF('Model inputs'!Z22="","",'Model inputs'!Z22),IF('Model inputs'!J6="","",'Model inputs'!J6)))+'Model inputs'!K16 -> -25 | L6: =IF(IF(DATE(2026,11,1)=DATE(2026,11,1),IF('Model inputs'!Z22="","",'Model inputs'!Z22),IF('Model inputs'!K6="","",'Model inputs'!K6))="",0,IF(DATE(2026,11,1)=DATE(2026,11,1),IF('Model inputs'!Z22="","",'Model inputs'!Z22),IF('Model inputs'!K6="","",'Model inputs'!K6)))+'Model inputs'!L16 -> -25 | M6: =IF(IF(DATE(2026,12,1)=DATE(2026,11,1),IF('Model inputs'!Z22="","",'Model inputs'!Z22),IF('Model inputs'!L6="","",'Model inputs'!L6))="",0,IF(DATE(2026,12,1)=DATE(2026,11,1),IF('Model inputs'!Z22="","",'Model inputs'!Z22),IF('Model inputs'!L6="","",'Model inputs'!L6)))+'Model inputs'!M16 -> 927 | N6: =IF(IF(DATE(2027,1,1)=DATE(2026,11,1),IF('Model inputs'!Z22="","",'Model inputs'!Z22),IF('Model inputs'!M6="","",'Model inputs'!M6))="",0,IF(DATE(2027,1,1)=DATE(2026,11,1),IF('Model inputs'!Z22="","",'Model inputs'!Z22),IF('Model inputs'!M6="","",'Model inputs'!M6)))+'Model inputs'!N16 -> 1879 | O6: =IF(IF(DATE(2027,2,1)=DATE(2026,11,1),IF('Model inputs'!Z22="","",'Model inputs'!Z22),IF('Model inputs'!N6="","",'Model inputs'!N6))="",0,IF(DATE(2027,2,1)=DATE(2026,11,1),IF('Model inputs'!Z22="","",'Model inputs'!Z22),IF('Model inputs'!N6="","",'Model inputs'!N6)))+'Model inputs'!O16 -> 2831 | P6: =IF(IF(DATE(2027,3,1)=DATE(2026,11,1),IF('Model inputs'!Z22="","",'Model inputs'!Z22),IF('Model inputs'!O6="","",'Model inputs'!O6))="",0,IF(DATE(2027,3,1)=DATE(2026,11,1),IF('Model inputs'!Z22="","",'Model inputs'!Z22),IF('Model inputs'!O6="","",'Model inputs'!O6)))+'Model inputs'!P16 -> 3783 | Q6: =IF(IF(DATE(2027,4,1)=DATE(2026,11,1),IF('Model inputs'!Z22="","",'Model inputs'!Z22),IF('Model inputs'!P6="","",'Model inputs'!P6))="",0,IF(DATE(2027,4,1)=DATE(2026,11,1),IF('Model inputs'!Z22="","",'Model inputs'!Z22),IF('Model inputs'!P6="","",'Model inputs'!P6)))+'Model inputs'!Q16 -> 4735 | R6: =IF(IF(DATE(2027,5,1)=DATE(2026,11,1),IF('Model inputs'!Z22="","",'Model inputs'!Z22),IF('Model inputs'!Q6="","",'Model inputs'!Q6))="",0,IF(DATE(2027,5,1)=DATE(2026,11,1),IF('Model inputs'!Z22="","",'Model inputs'!Z22),IF('Model inputs'!Q6="","",'Model inputs'!Q6)))+'Model inputs'!R16 -> 5687 | S6: =IF(IF(DATE(2027,6,1)=DATE(2026,11,1),IF('Model inputs'!Z22="","",'Model inputs'!Z22),IF('Model inputs'!R6="","",'Model inputs'!R6))="",0,IF(DATE(2027,6,1)=DATE(2026,11,1),IF('Model inputs'!Z22="","",'Model inputs'!Z22),IF('Model inputs'!R6="","",'Model inputs'!R6)))+'Model inputs'!S16 -> 6639 | T6: =IF(IF(DATE(2027,7,1)=DATE(2026,11,1),IF('Model inputs'!Z22="","",'Model inputs'!Z22),IF('Model inputs'!S6="","",'Model inputs'!S6))="",0,IF(DATE(2027,7,1)=DATE(2026,11,1),IF('Model inputs'!Z22="","",'Model inputs'!Z22),IF('Model inputs'!S6="","",'Model inputs'!S6)))+'Model inputs'!T16 -> 7591 | U6: =IF(IF(DATE(2027,8,1)=DATE(2026,11,1),IF('Model inputs'!Z22="","",'Model inputs'!Z22),IF('Model inputs'!T6="","",'Model inputs'!T6))="",0,IF(DATE(2027,8,1)=DATE(2026,11,1),IF('Model inputs'!Z22="","",'Model inputs'!Z22),IF('Model inputs'!T6="","",'Model inputs'!T6)))+'Model inputs'!U16 -> 8543 | V6: =IF(IF(DATE(2027,9,1)=DATE(2026,11,1),IF('Model inputs'!Z22="","",'Model inputs'!Z22),IF('Model inputs'!U6="","",'Model inputs'!U6))="",0,IF(DATE(2027,9,1)=DATE(2026,11,1),IF('Model inputs'!Z22="","",'Model inputs'!Z22),IF('Model inputs'!U6="","",'Model inputs'!U6)))+'Model inputs'!V16 -> 9495 | W6: =IF(IF(DATE(2027,10,1)=DATE(2026,11,1),IF('Model inputs'!Z22="","",'Model inputs'!Z22),IF('Model inputs'!V6="","",'Model inputs'!V6))="",0,IF(DATE(2027,10,1)=DATE(2026,11,1),IF('Model inputs'!Z22="","",'Model inputs'!Z22),IF('Model inputs'!V6="","",'Model inputs'!V6)))+'Model inputs'!W16 -> 10447 | X6: =IF(IF(DATE(2027,11,1)=DATE(2026,11,1),IF('Model inputs'!Z22="","",'Model inputs'!Z22),IF('Model inputs'!W6="","",'Model inputs'!W6))="",0,IF(DATE(2027,11,1)=DATE(2026,11,1),IF('Model inputs'!Z22="","",'Model inputs'!Z22),IF('Model inputs'!W6="","",'Model inputs'!W6)))+'Model inputs'!X16 -> 10422 | Y6: =IF(IF(DATE(2027,12,1)=DATE(2026,11,1),IF('Model inputs'!Z22="","",'Model inputs'!Z22),IF('Model inputs'!X6="","",'Model inputs'!X6))="",0,IF(DATE(2027,12,1)=DATE(2026,11,1),IF('Model inputs'!Z22="","",'Model inputs'!Z22),IF('Model inputs'!X6="","",'Model inputs'!X6)))+'Model inputs'!Y16 -> 10397
A7: Assumed ending cash · Higher price | B7: 0 | C7: 0 | D7: 0 | E7: 0 | F7: 0 | G7: 0 | H7: 0 | I7: 0 | J7: 0 | K7: =IF(IF(DATE(2026,10,1)=DATE(2026,11,1),IF('Model inputs'!Z23="","",'Model inputs'!Z23),IF('Model inputs'!J7="","",'Model inputs'!J7))="",0,IF(DATE(2026,10,1)=DATE(2026,11,1),IF('Model inputs'!Z23="","",'Model inputs'!Z23),IF('Model inputs'!J7="","",'Model inputs'!J7)))+'Model inputs'!K17 -> -25 | L7: =IF(IF(DATE(2026,11,1)=DATE(2026,11,1),IF('Model inputs'!Z23="","",'Model inputs'!Z23),IF('Model inputs'!K7="","",'Model inputs'!K7))="",0,IF(DATE(2026,11,1)=DATE(2026,11,1),IF('Model inputs'!Z23="","",'Model inputs'!Z23),IF('Model inputs'!K7="","",'Model inputs'!K7)))+'Model inputs'!L17 -> -25 | M7: =IF(IF(DATE(2026,12,1)=DATE(2026,11,1),IF('Model inputs'!Z23="","",'Model inputs'!Z23),IF('Model inputs'!L7="","",'Model inputs'!L7))="",0,IF(DATE(2026,12,1)=DATE(2026,11,1),IF('Model inputs'!Z23="","",'Model inputs'!Z23),IF('Model inputs'!L7="","",'Model inputs'!L7)))+'Model inputs'!M17 -> 1527 | N7: =IF(IF(DATE(2027,1,1)=DATE(2026,11,1),IF('Model inputs'!Z23="","",'Model inputs'!Z23),IF('Model inputs'!M7="","",'Model inputs'!M7))="",0,IF(DATE(2027,1,1)=DATE(2026,11,1),IF('Model inputs'!Z23="","",'Model inputs'!Z23),IF('Model inputs'!M7="","",'Model inputs'!M7)))+'Model inputs'!N17 -> 3079 | O7: =IF(IF(DATE(2027,2,1)=DATE(2026,11,1),IF('Model inputs'!Z23="","",'Model inputs'!Z23),IF('Model inputs'!N7="","",'Model inputs'!N7))="",0,IF(DATE(2027,2,1)=DATE(2026,11,1),IF('Model inputs'!Z23="","",'Model inputs'!Z23),IF('Model inputs'!N7="","",'Model inputs'!N7)))+'Model inputs'!O17 -> 4631 | P7: =IF(IF(DATE(2027,3,1)=DATE(2026,11,1),IF('Model inputs'!Z23="","",'Model inputs'!Z23),IF('Model inputs'!O7="","",'Model inputs'!O7))="",0,IF(DATE(2027,3,1)=DATE(2026,11,1),IF('Model inputs'!Z23="","",'Model inputs'!Z23),IF('Model inputs'!O7="","",'Model inputs'!O7)))+'Model inputs'!P17 -> 6183 | Q7: =IF(IF(DATE(2027,4,1)=DATE(2026,11,1),IF('Model inputs'!Z23="","",'Model inputs'!Z23),IF('Model inputs'!P7="","",'Model inputs'!P7))="",0,IF(DATE(2027,4,1)=DATE(2026,11,1),IF('Model inputs'!Z23="","",'Model inputs'!Z23),IF('Model inputs'!P7="","",'Model inputs'!P7)))+'Model inputs'!Q17 -> 7735 | R7: =IF(IF(DATE(2027,5,1)=DATE(2026,11,1),IF('Model inputs'!Z23="","",'Model inputs'!Z23),IF('Model inputs'!Q7="","",'Model inputs'!Q7))="",0,IF(DATE(2027,5,1)=DATE(2026,11,1),IF('Model inputs'!Z23="","",'Model inputs'!Z23),IF('Model inputs'!Q7="","",'Model inputs'!Q7)))+'Model inputs'!R17 -> 9287 | S7: =IF(IF(DATE(2027,6,1)=DATE(2026,11,1),IF('Model inputs'!Z23="","",'Model inputs'!Z23),IF('Model inputs'!R7="","",'Model inputs'!R7))="",0,IF(DATE(2027,6,1)=DATE(2026,11,1),IF('Model inputs'!Z23="","",'Model inputs'!Z23),IF('Model inputs'!R7="","",'Model inputs'!R7)))+'Model inputs'!S17 -> 10839 | T7: =IF(IF(DATE(2027,7,1)=DATE(2026,11,1),IF('Model inputs'!Z23="","",'Model inputs'!Z23),IF('Model inputs'!S7="","",'Model inputs'!S7))="",0,IF(DATE(2027,7,1)=DATE(2026,11,1),IF('Model inputs'!Z23="","",'Model inputs'!Z23),IF('Model inputs'!S7="","",'Model inputs'!S7)))+'Model inputs'!T17 -> 12391 | U7: =IF(IF(DATE(2027,8,1)=DATE(2026,11,1),IF('Model inputs'!Z23="","",'Model inputs'!Z23),IF('Model inputs'!T7="","",'Model inputs'!T7))="",0,IF(DATE(2027,8,1)=DATE(2026,11,1),IF('Model inputs'!Z23="","",'Model inputs'!Z23),IF('Model inputs'!T7="","",'Model inputs'!T7)))+'Model inputs'!U17 -> 13943 | V7: =IF(IF(DATE(2027,9,1)=DATE(2026,11,1),IF('Model inputs'!Z23="","",'Model inputs'!Z23),IF('Model inputs'!U7="","",'Model inputs'!U7))="",0,IF(DATE(2027,9,1)=DATE(2026,11,1),IF('Model inputs'!Z23="","",'Model inputs'!Z23),IF('Model inputs'!U7="","",'Model inputs'!U7)))+'Model inputs'!V17 -> 15495 | W7: =IF(IF(DATE(2027,10,1)=DATE(2026,11,1),IF('Model inputs'!Z23="","",'Model inputs'!Z23),IF('Model inputs'!V7="","",'Model inputs'!V7))="",0,IF(DATE(2027,10,1)=DATE(2026,11,1),IF('Model inputs'!Z23="","",'Model inputs'!Z23),IF('Model inputs'!V7="","",'Model inputs'!V7)))+'Model inputs'!W17 -> 17047 | X7: =IF(IF(DATE(2027,11,1)=DATE(2026,11,1),IF('Model inputs'!Z23="","",'Model inputs'!Z23),IF('Model inputs'!W7="","",'Model inputs'!W7))="",0,IF(DATE(2027,11,1)=DATE(2026,11,1),IF('Model inputs'!Z23="","",'Model inputs'!Z23),IF('Model inputs'!W7="","",'Model inputs'!W7)))+'Model inputs'!X17 -> 17022 | Y7: =IF(IF(DATE(2027,12,1)=DATE(2026,11,1),IF('Model inputs'!Z23="","",'Model inputs'!Z23),IF('Model inputs'!X7="","",'Model inputs'!X7))="",0,IF(DATE(2027,12,1)=DATE(2026,11,1),IF('Model inputs'!Z23="","",'Model inputs'!Z23),IF('Model inputs'!X7="","",'Model inputs'!X7)))+'Model inputs'!Y17 -> 16997
A8: Assumed revenue · Main Scenario | B8: 0 | C8: 0 | D8: 0 | E8: 0 | F8: 0 | G8: 0 | H8: 0 | I8: 0 | J8: 0 | K8: ='Model inputs'!K20*'Model inputs'!K18 -> 0 | L8: ='Model inputs'!L20*'Model inputs'!L18 -> 0 | M8: ='Model inputs'!M20*'Model inputs'!M18 -> 980 | N8: ='Model inputs'!N20*'Model inputs'!N18 -> 980 | O8: ='Model inputs'!O20*'Model inputs'!O18 -> 980 | P8: ='Model inputs'!P20*'Model inputs'!P18 -> 980 | Q8: ='Model inputs'!Q20*'Model inputs'!Q18 -> 980 | R8: ='Model inputs'!R20*'Model inputs'!R18 -> 980 | ... Y8: ='Model inputs'!Y20*'Model inputs'!Y18 -> 0
A9: Assumed revenue · Higher price | B9: 0 | C9: 0 | D9: 0 | E9: 0 | F9: 0 | G9: 0 | H9: 0 | I9: 0 | J9: 0 | K9: ='Model inputs'!K21*'Model inputs'!K19 -> 0 | L9: ='Model inputs'!L21*'Model inputs'!L19 -> 0 | M9: ='Model inputs'!M21*'Model inputs'!M19 -> 1580 | N9: ='Model inputs'!N21*'Model inputs'!N19 -> 1580 | O9: ='Model inputs'!O21*'Model inputs'!O19 -> 1580 | P9: ='Model inputs'!P21*'Model inputs'!P19 -> 1580 | Q9: ='Model inputs'!Q21*'Model inputs'!Q19 -> 1580 | R9: ='Model inputs'!R21*'Model inputs'!R19 -> 1580 | ... Y9: ='Model inputs'!Y21*'Model inputs'!Y19 -> 0
A10: Assumed total cost · Main Scenario | B10: 0 | C10: 0 | D10: 0 | E10: 0 | F10: 0 | G10: 0 | H10: 0 | I10: 0 | J10: 0 | K10: ='Model inputs'!K14+'Model inputs'!K12 -> 25 | L10: ='Model inputs'!L14+'Model inputs'!L12 -> 25 | M10: ='Model inputs'!M14+'Model inputs'!M12 -> 28 | N10: ='Model inputs'!N14+'Model inputs'!N12 -> 28 | O10: ='Model inputs'!O14+'Model inputs'!O12 -> 28 | P10: ='Model inputs'!P14+'Model inputs'!P12 -> 28 | Q10: ='Model inputs'!Q14+'Model inputs'!Q12 -> 28 | R10: ='Model inputs'!R14+'Model inputs'!R12 -> 28 | ... Y10: ='Model inputs'!Y14+'Model inputs'!Y12 -> 25
A11: Assumed total cost · Higher price | B11: 0 | C11: 0 | D11: 0 | E11: 0 | F11: 0 | G11: 0 | H11: 0 | I11: 0 | J11: 0 | K11: ='Model inputs'!K15+'Model inputs'!K13 -> 25 | L11: ='Model inputs'!L15+'Model inputs'!L13 -> 25 | M11: ='Model inputs'!M15+'Model inputs'!M13 -> 28 | N11: ='Model inputs'!N15+'Model inputs'!N13 -> 28 | O11: ='Model inputs'!O15+'Model inputs'!O13 -> 28 | P11: ='Model inputs'!P15+'Model inputs'!P13 -> 28 | Q11: ='Model inputs'!Q15+'Model inputs'!Q13 -> 28 | R11: ='Model inputs'!R15+'Model inputs'!R13 -> 28 | ... Y11: ='Model inputs'!Y15+'Model inputs'!Y13 -> 25
A12: Assumed infrastructure · Assumed total cost · Main Scenario · Main Scenario | B12: 0 | C12: 0 | D12: 0 | E12: 0 | F12: 0 | G12: 0 | H12: 0 | I12: 0 | J12: 0 | K12: =IF('Model inputs'!Z26="","",'Model inputs'!Z26) -> 25 | L12: =IF('Model inputs'!Z26="","",'Model inputs'!Z26) -> 25 | M12: =IF('Model inputs'!Z26="","",'Model inputs'!Z26) -> 25 | N12: =IF('Model inputs'!Z26="","",'Model inputs'!Z26) -> 25 | O12: =IF('Model inputs'!Z26="","",'Model inputs'!Z26) -> 25 | P12: =IF('Model inputs'!Z26="","",'Model inputs'!Z26) -> 25 | Q12: =IF('Model inputs'!Z26="","",'Model inputs'!Z26) -> 25 | R12: =IF('Model inputs'!Z26="","",'Model inputs'!Z26) -> 25 | S12: =IF('Model inputs'!Z26="","",'Model inputs'!Z26) -> 25 | T12: =IF('Model inputs'!Z26="","",'Model inputs'!Z26) -> 25 | U12: =IF('Model inputs'!Z26="","",'Model inputs'!Z26) -> 25 | V12: =IF('Model inputs'!Z26="","",'Model inputs'!Z26) -> 25 | W12: =IF('Model inputs'!Z26="","",'Model inputs'!Z26) -> 25 | X12: =IF('Model inputs'!Z26="","",'Model inputs'!Z26) -> 25 | Y12: =IF('Model inputs'!Z26="","",'Model inputs'!Z26) -> 25
A13: Assumed infrastructure · Assumed total cost · Higher price · Higher price | B13: 0 | C13: 0 | D13: 0 | E13: 0 | F13: 0 | G13: 0 | H13: 0 | I13: 0 | J13: 0 | K13: =IF('Model inputs'!Z27="","",'Model inputs'!Z27) -> 25 | L13: =IF('Model inputs'!Z27="","",'Model inputs'!Z27) -> 25 | M13: =IF('Model inputs'!Z27="","",'Model inputs'!Z27) -> 25 | N13: =IF('Model inputs'!Z27="","",'Model inputs'!Z27) -> 25 | O13: =IF('Model inputs'!Z27="","",'Model inputs'!Z27) -> 25 | P13: =IF('Model inputs'!Z27="","",'Model inputs'!Z27) -> 25 | Q13: =IF('Model inputs'!Z27="","",'Model inputs'!Z27) -> 25 | R13: =IF('Model inputs'!Z27="","",'Model inputs'!Z27) -> 25 | S13: =IF('Model inputs'!Z27="","",'Model inputs'!Z27) -> 25 | T13: =IF('Model inputs'!Z27="","",'Model inputs'!Z27) -> 25 | U13: =IF('Model inputs'!Z27="","",'Model inputs'!Z27) -> 25 | V13: =IF('Model inputs'!Z27="","",'Model inputs'!Z27) -> 25 | W13: =IF('Model inputs'!Z27="","",'Model inputs'!Z27) -> 25 | X13: =IF('Model inputs'!Z27="","",'Model inputs'!Z27) -> 25 | Y13: =IF('Model inputs'!Z27="","",'Model inputs'!Z27) -> 25
A14: Assumed model cost · Assumed total cost · Main Scenario · Main Scenario | B14: 0 | C14: 0 | D14: 0 | E14: 0 | F14: 0 | G14: 0 | H14: 0 | I14: 0 | J14: 0 | K14: ='Model inputs'!Z24*'Model inputs'!K18 -> 0 | L14: ='Model inputs'!Z24*'Model inputs'!L18 -> 0 | M14: ='Model inputs'!Z24*'Model inputs'!M18 -> 3 | N14: ='Model inputs'!Z24*'Model inputs'!N18 -> 3 | O14: ='Model inputs'!Z24*'Model inputs'!O18 -> 3 | P14: ='Model inputs'!Z24*'Model inputs'!P18 -> 3 | Q14: ='Model inputs'!Z24*'Model inputs'!Q18 -> 3 | R14: ='Model inputs'!Z24*'Model inputs'!R18 -> 3 | S14: ='Model inputs'!Z24*'Model inputs'!S18 -> 3 | T14: ='Model inputs'!Z24*'Model inputs'!T18 -> 3 | U14: ='Model inputs'!Z24*'Model inputs'!U18 -> 3 | V14: ='Model inputs'!Z24*'Model inputs'!V18 -> 3 | W14: ='Model inputs'!Z24*'Model inputs'!W18 -> 3 | X14: ='Model inputs'!Z24*'Model inputs'!X18 -> 0 | Y14: ='Model inputs'!Z24*'Model inputs'!Y18 -> 0
A15: Assumed model cost · Assumed total cost · Higher price · Higher price | B15: 0 | C15: 0 | D15: 0 | E15: 0 | F15: 0 | G15: 0 | H15: 0 | I15: 0 | J15: 0 | K15: ='Model inputs'!Z25*'Model inputs'!K19 -> 0 | L15: ='Model inputs'!Z25*'Model inputs'!L19 -> 0 | M15: ='Model inputs'!Z25*'Model inputs'!M19 -> 3 | N15: ='Model inputs'!Z25*'Model inputs'!N19 -> 3 | O15: ='Model inputs'!Z25*'Model inputs'!O19 -> 3 | P15: ='Model inputs'!Z25*'Model inputs'!P19 -> 3 | Q15: ='Model inputs'!Z25*'Model inputs'!Q19 -> 3 | R15: ='Model inputs'!Z25*'Model inputs'!R19 -> 3 | S15: ='Model inputs'!Z25*'Model inputs'!S19 -> 3 | T15: ='Model inputs'!Z25*'Model inputs'!T19 -> 3 | U15: ='Model inputs'!Z25*'Model inputs'!U19 -> 3 | V15: ='Model inputs'!Z25*'Model inputs'!V19 -> 3 | W15: ='Model inputs'!Z25*'Model inputs'!W19 -> 3 | X15: ='Model inputs'!Z25*'Model inputs'!X19 -> 0 | Y15: ='Model inputs'!Z25*'Model inputs'!Y19 -> 0
A16: Assumed operating result · Assumed ending cash · Main Scenario · Main Scenario | B16: 0 | C16: 0 | D16: 0 | E16: 0 | F16: 0 | G16: 0 | H16: 0 | I16: 0 | J16: 0 | K16: ='Model inputs'!K8-'Model inputs'!K10 -> -25 | L16: ='Model inputs'!L8-'Model inputs'!L10 -> -25 | M16: ='Model inputs'!M8-'Model inputs'!M10 -> 952 | N16: ='Model inputs'!N8-'Model inputs'!N10 -> 952 | O16: ='Model inputs'!O8-'Model inputs'!O10 -> 952 | P16: ='Model inputs'!P8-'Model inputs'!P10 -> 952 | Q16: ='Model inputs'!Q8-'Model inputs'!Q10 -> 952 | R16: ='Model inputs'!R8-'Model inputs'!R10 -> 952 | ... Y16: ='Model inputs'!Y8-'Model inputs'!Y10 -> -25
A17: Assumed operating result · Assumed ending cash · Higher price · Higher price | B17: 0 | C17: 0 | D17: 0 | E17: 0 | F17: 0 | G17: 0 | H17: 0 | I17: 0 | J17: 0 | K17: ='Model inputs'!K9-'Model inputs'!K11 -> -25 | L17: ='Model inputs'!L9-'Model inputs'!L11 -> -25 | M17: ='Model inputs'!M9-'Model inputs'!M11 -> 1552 | N17: ='Model inputs'!N9-'Model inputs'!N11 -> 1552 | O17: ='Model inputs'!O9-'Model inputs'!O11 -> 1552 | P17: ='Model inputs'!P9-'Model inputs'!P11 -> 1552 | Q17: ='Model inputs'!Q9-'Model inputs'!Q11 -> 1552 | R17: ='Model inputs'!R9-'Model inputs'!R11 -> 1552 | ... Y17: ='Model inputs'!Y9-'Model inputs'!Y11 -> -25
A18: Assumed paid runs · Assumed revenue · Main Scenario · Main Scenario | B18: 0 | C18: 0 | D18: 0 | E18: 0 | F18: 0 | G18: 0 | H18: 0 | I18: 0 | J18: 0 | K18: 0 | L18: =0 -> 0 | M18: =20 -> 20 | N18: =20 -> 20 | O18: =20 -> 20 | P18: =20 -> 20 | Q18: =20 -> 20 | R18: =20 -> 20 | S18: =20 -> 20 | T18: =20 -> 20 | ... W18: =20 -> 20 | X18: 0 | Y18: 0
A19: Assumed paid runs · Assumed revenue · Higher price · Higher price | B19: 0 | C19: 0 | D19: 0 | E19: 0 | F19: 0 | G19: 0 | H19: 0 | I19: 0 | J19: 0 | K19: 0 | L19: ='Model inputs'!L18 -> 0 | M19: ='Model inputs'!M18 -> 20 | N19: ='Model inputs'!N18 -> 20 | O19: ='Model inputs'!O18 -> 20 | P19: ='Model inputs'!P18 -> 20 | Q19: ='Model inputs'!Q18 -> 20 | R19: ='Model inputs'!R18 -> 20 | S19: ='Model inputs'!S18 -> 20 | ... W19: ='Model inputs'!W18 -> 20 | X19: 0 | Y19: 0
A20: Assumed price · Assumed revenue · Main Scenario · Main Scenario | B20: =IF('Model inputs'!Z28="","",'Model inputs'!Z28) -> 49 | C20: =IF('Model inputs'!Z28="","",'Model inputs'!Z28) -> 49 | D20: =IF('Model inputs'!Z28="","",'Model inputs'!Z28) -> 49 | E20: =IF('Model inputs'!Z28="","",'Model inputs'!Z28) -> 49 | F20: =IF('Model inputs'!Z28="","",'Model inputs'!Z28) -> 49 | G20: =IF('Model inputs'!Z28="","",'Model inputs'!Z28) -> 49 | H20: =IF('Model inputs'!Z28="","",'Model inputs'!Z28) -> 49 | I20: =IF('Model inputs'!Z28="","",'Model inputs'!Z28) -> 49 | J20: =IF('Model inputs'!Z28="","",'Model inputs'!Z28) -> 49 | K20: =IF('Model inputs'!Z28="","",'Model inputs'!Z28) -> 49 | L20: =IF('Model inputs'!Z28="","",'Model inputs'!Z28) -> 49 | M20: =IF('Model inputs'!Z28="","",'Model inputs'!Z28) -> 49 | N20: =IF('Model inputs'!Z28="","",'Model inputs'!Z28) -> 49 | O20: =IF('Model inputs'!Z28="","",'Model inputs'!Z28) -> 49 | P20: =IF('Model inputs'!Z28="","",'Model inputs'!Z28) -> 49 | Q20: =IF('Model inputs'!Z28="","",'Model inputs'!Z28) -> 49 | R20: =IF('Model inputs'!Z28="","",'Model inputs'!Z28) -> 49 | S20: =IF('Model inputs'!Z28="","",'Model inputs'!Z28) -> 49 | T20: =IF('Model inputs'!Z28="","",'Model inputs'!Z28) -> 49 | U20: =IF('Model inputs'!Z28="","",'Model inputs'!Z28) -> 49 | V20: =IF('Model inputs'!Z28="","",'Model inputs'!Z28) -> 49 | W20: =IF('Model inputs'!Z28="","",'Model inputs'!Z28) -> 49 | X20: =IF('Model inputs'!Z28="","",'Model inputs'!Z28) -> 49 | Y20: =IF('Model inputs'!Z28="","",'Model inputs'!Z28) -> 49
A21: Assumed price · Assumed revenue · Higher price · Higher price | B21: =IF('Model inputs'!Z29="","",'Model inputs'!Z29) -> 79 | C21: =IF('Model inputs'!Z29="","",'Model inputs'!Z29) -> 79 | D21: =IF('Model inputs'!Z29="","",'Model inputs'!Z29) -> 79 | E21: =IF('Model inputs'!Z29="","",'Model inputs'!Z29) -> 79 | F21: =IF('Model inputs'!Z29="","",'Model inputs'!Z29) -> 79 | G21: =IF('Model inputs'!Z29="","",'Model inputs'!Z29) -> 79 | H21: =IF('Model inputs'!Z29="","",'Model inputs'!Z29) -> 79 | I21: =IF('Model inputs'!Z29="","",'Model inputs'!Z29) -> 79 | J21: =IF('Model inputs'!Z29="","",'Model inputs'!Z29) -> 79 | K21: =IF('Model inputs'!Z29="","",'Model inputs'!Z29) -> 79 | L21: =IF('Model inputs'!Z29="","",'Model inputs'!Z29) -> 79 | M21: =IF('Model inputs'!Z29="","",'Model inputs'!Z29) -> 79 | N21: =IF('Model inputs'!Z29="","",'Model inputs'!Z29) -> 79 | O21: =IF('Model inputs'!Z29="","",'Model inputs'!Z29) -> 79 | P21: =IF('Model inputs'!Z29="","",'Model inputs'!Z29) -> 79 | Q21: =IF('Model inputs'!Z29="","",'Model inputs'!Z29) -> 79 | R21: =IF('Model inputs'!Z29="","",'Model inputs'!Z29) -> 79 | S21: =IF('Model inputs'!Z29="","",'Model inputs'!Z29) -> 79 | T21: =IF('Model inputs'!Z29="","",'Model inputs'!Z29) -> 79 | U21: =IF('Model inputs'!Z29="","",'Model inputs'!Z29) -> 79 | V21: =IF('Model inputs'!Z29="","",'Model inputs'!Z29) -> 79 | W21: =IF('Model inputs'!Z29="","",'Model inputs'!Z29) -> 79 | X21: =IF('Model inputs'!Z29="","",'Model inputs'!Z29) -> 79 | Y21: =IF('Model inputs'!Z29="","",'Model inputs'!Z29) -> 79
A22: Assumed starting cash · Assumed ending cash · Main Scenario · Main Scenario | Z22: =0 -> 0
A23: Assumed starting cash · Assumed ending cash · Higher price · Higher price | Z23: ='Model inputs'!Z22 -> 0
A24: Assumed model cost per run · Assumed model cost · Assumed total cost · Main Scenario · Main Scenario · Main Scenario | Z24: =0.15 -> 0.15
A25: Assumed model cost per run · Assumed model cost · Assumed total cost · Higher price · Higher price · Higher price | Z25: ='Model inputs'!Z24 -> 0.15
A26: Assumed monthly infrastructure input · Assumed infrastructure · Assumed total cost · Main Scenario · Main Scenario · Main Scenario | Z26: =25 -> 25
A27: Assumed monthly infrastructure input · Assumed infrastructure · Assumed total cost · Higher price · Higher price · Higher price | Z27: ='Model inputs'!Z26 -> 25
A28: Assumed recovery price · Assumed price · Assumed revenue · Main Scenario · Main Scenario · Main Scenario | Z28: =49 -> 49
A29: Assumed recovery price · Assumed price · Assumed revenue · Higher price · Higher price · Higher price | Z29: =79 -> 79
