Workbook

Sheet Nightshift monthly assumed fore
A1: Nightshift monthly assumed forecast
A2: Nightshift — Monthly baseline · Main Scenario
A4: Variable / dimension | B4: 2026-11 | C4: 2026-12 | D4: 2027-01 | E4: 2027-02 | F4: 2027-03 | G4: 2027-04 | H4: 2027-05 | I4: 2027-06 | J4: 2027-07 | K4: 2027-08 | L4: 2027-09 | M4: 2027-10
A5: Assumed price | B5: =IF('Model inputs'!P14="","",'Model inputs'!P14) -> 49 | C5: =IF('Model inputs'!P14="","",'Model inputs'!P14) -> 49 | D5: =IF('Model inputs'!P14="","",'Model inputs'!P14) -> 49 | E5: =IF('Model inputs'!P14="","",'Model inputs'!P14) -> 49 | F5: =IF('Model inputs'!P14="","",'Model inputs'!P14) -> 49 | G5: =IF('Model inputs'!P14="","",'Model inputs'!P14) -> 49 | H5: =IF('Model inputs'!P14="","",'Model inputs'!P14) -> 49 | I5: =IF('Model inputs'!P14="","",'Model inputs'!P14) -> 49 | J5: =IF('Model inputs'!P14="","",'Model inputs'!P14) -> 49 | K5: =IF('Model inputs'!P14="","",'Model inputs'!P14) -> 49 | L5: =IF('Model inputs'!P14="","",'Model inputs'!P14) -> 49 | M5: =IF('Model inputs'!P14="","",'Model inputs'!P14) -> 49
A6: Assumed paid runs | B6: =0 -> 0 | C6: =20 -> 20 | D6: =20 -> 20 | E6: =20 -> 20 | F6: =20 -> 20 | G6: =20 -> 20 | H6: =20 -> 20 | I6: =20 -> 20 | J6: =20 -> 20 | ... M6: =20 -> 20
A7: Assumed revenue | B7: ='Nightshift monthly assumed fore'!B5*'Nightshift monthly assumed fore'!B6 -> 0 | C7: ='Nightshift monthly assumed fore'!C5*'Nightshift monthly assumed fore'!C6 -> 980 | D7: ='Nightshift monthly assumed fore'!D5*'Nightshift monthly assumed fore'!D6 -> 980 | E7: ='Nightshift monthly assumed fore'!E5*'Nightshift monthly assumed fore'!E6 -> 980 | F7: ='Nightshift monthly assumed fore'!F5*'Nightshift monthly assumed fore'!F6 -> 980 | G7: ='Nightshift monthly assumed fore'!G5*'Nightshift monthly assumed fore'!G6 -> 980 | H7: ='Nightshift monthly assumed fore'!H5*'Nightshift monthly assumed fore'!H6 -> 980 | I7: ='Nightshift monthly assumed fore'!I5*'Nightshift monthly assumed fore'!I6 -> 980 | ... M7: ='Nightshift monthly assumed fore'!M5*'Nightshift monthly assumed fore'!M6 -> 980
A8: Assumed model cost | B8: ='Model inputs'!P9*'Nightshift monthly assumed fore'!B6 -> 0 | C8: ='Model inputs'!P9*'Nightshift monthly assumed fore'!C6 -> 3 | D8: ='Model inputs'!P9*'Nightshift monthly assumed fore'!D6 -> 3 | E8: ='Model inputs'!P9*'Nightshift monthly assumed fore'!E6 -> 3 | F8: ='Model inputs'!P9*'Nightshift monthly assumed fore'!F6 -> 3 | G8: ='Model inputs'!P9*'Nightshift monthly assumed fore'!G6 -> 3 | H8: ='Model inputs'!P9*'Nightshift monthly assumed fore'!H6 -> 3 | I8: ='Model inputs'!P9*'Nightshift monthly assumed fore'!I6 -> 3 | J8: ='Model inputs'!P9*'Nightshift monthly assumed fore'!J6 -> 3 | K8: ='Model inputs'!P9*'Nightshift monthly assumed fore'!K6 -> 3 | L8: ='Model inputs'!P9*'Nightshift monthly assumed fore'!L6 -> 3 | M8: ='Model inputs'!P9*'Nightshift monthly assumed fore'!M6 -> 3
A9: Assumed infrastructure | B9: =IF('Model inputs'!P10="","",'Model inputs'!P10) -> 25 | C9: =IF('Model inputs'!P10="","",'Model inputs'!P10) -> 25 | D9: =IF('Model inputs'!P10="","",'Model inputs'!P10) -> 25 | E9: =IF('Model inputs'!P10="","",'Model inputs'!P10) -> 25 | F9: =IF('Model inputs'!P10="","",'Model inputs'!P10) -> 25 | G9: =IF('Model inputs'!P10="","",'Model inputs'!P10) -> 25 | H9: =IF('Model inputs'!P10="","",'Model inputs'!P10) -> 25 | I9: =IF('Model inputs'!P10="","",'Model inputs'!P10) -> 25 | J9: =IF('Model inputs'!P10="","",'Model inputs'!P10) -> 25 | K9: =IF('Model inputs'!P10="","",'Model inputs'!P10) -> 25 | L9: =IF('Model inputs'!P10="","",'Model inputs'!P10) -> 25 | M9: =IF('Model inputs'!P10="","",'Model inputs'!P10) -> 25
A10: Assumed total cost | B10: ='Nightshift monthly assumed fore'!B8+'Nightshift monthly assumed fore'!B9 -> 25 | C10: ='Nightshift monthly assumed fore'!C8+'Nightshift monthly assumed fore'!C9 -> 28 | D10: ='Nightshift monthly assumed fore'!D8+'Nightshift monthly assumed fore'!D9 -> 28 | E10: ='Nightshift monthly assumed fore'!E8+'Nightshift monthly assumed fore'!E9 -> 28 | F10: ='Nightshift monthly assumed fore'!F8+'Nightshift monthly assumed fore'!F9 -> 28 | G10: ='Nightshift monthly assumed fore'!G8+'Nightshift monthly assumed fore'!G9 -> 28 | H10: ='Nightshift monthly assumed fore'!H8+'Nightshift monthly assumed fore'!H9 -> 28 | I10: ='Nightshift monthly assumed fore'!I8+'Nightshift monthly assumed fore'!I9 -> 28 | ... M10: ='Nightshift monthly assumed fore'!M8+'Nightshift monthly assumed fore'!M9 -> 28
A11: Assumed operating result | B11: ='Nightshift monthly assumed fore'!B7-'Nightshift monthly assumed fore'!B10 -> -25 | C11: ='Nightshift monthly assumed fore'!C7-'Nightshift monthly assumed fore'!C10 -> 952 | D11: ='Nightshift monthly assumed fore'!D7-'Nightshift monthly assumed fore'!D10 -> 952 | E11: ='Nightshift monthly assumed fore'!E7-'Nightshift monthly assumed fore'!E10 -> 952 | F11: ='Nightshift monthly assumed fore'!F7-'Nightshift monthly assumed fore'!F10 -> 952 | G11: ='Nightshift monthly assumed fore'!G7-'Nightshift monthly assumed fore'!G10 -> 952 | H11: ='Nightshift monthly assumed fore'!H7-'Nightshift monthly assumed fore'!H10 -> 952 | I11: ='Nightshift monthly assumed fore'!I7-'Nightshift monthly assumed fore'!I10 -> 952 | ... M11: ='Nightshift monthly assumed fore'!M7-'Nightshift monthly assumed fore'!M10 -> 952
A12: Assumed ending cash | B12: =IF(IF(DATE(2026,11,1)=DATE(2026,11,1),IF('Model inputs'!P16="","",'Model inputs'!P16),IF('Model inputs'!C6="","",'Model inputs'!C6))="",0,IF(DATE(2026,11,1)=DATE(2026,11,1),IF('Model inputs'!P16="","",'Model inputs'!P16),IF('Model inputs'!C6="","",'Model inputs'!C6)))+'Nightshift monthly assumed fore'!B11 -> -25 | C12: =IF(IF(DATE(2026,12,1)=DATE(2026,11,1),IF('Model inputs'!P16="","",'Model inputs'!P16),IF('Nightshift monthly assumed fore'!B12="","",'Nightshift monthly assumed fore'!B12))="",0,IF(DATE(2026,12,1)=DATE(2026,11,1),IF('Model inputs'!P16="","",'Model inputs'!P16),IF('Nightshift monthly assumed fore'!B12="","",'Nightshift monthly assumed fore'!B12)))+'Nightshift monthly assumed fore'!C11 -> 927 | D12: =IF(IF(DATE(2027,1,1)=DATE(2026,11,1),IF('Model inputs'!P16="","",'Model inputs'!P16),IF('Nightshift monthly assumed fore'!C12="","",'Nightshift monthly assumed fore'!C12))="",0,IF(DATE(2027,1,1)=DATE(2026,11,1),IF('Model inputs'!P16="","",'Model inputs'!P16),IF('Nightshift monthly assumed fore'!C12="","",'Nightshift monthly assumed fore'!C12)))+'Nightshift monthly assumed fore'!D11 -> 1879 | E12: =IF(IF(DATE(2027,2,1)=DATE(2026,11,1),IF('Model inputs'!P16="","",'Model inputs'!P16),IF('Nightshift monthly assumed fore'!D12="","",'Nightshift monthly assumed fore'!D12))="",0,IF(DATE(2027,2,1)=DATE(2026,11,1),IF('Model inputs'!P16="","",'Model inputs'!P16),IF('Nightshift monthly assumed fore'!D12="","",'Nightshift monthly assumed fore'!D12)))+'Nightshift monthly assumed fore'!E11 -> 2831 | F12: =IF(IF(DATE(2027,3,1)=DATE(2026,11,1),IF('Model inputs'!P16="","",'Model inputs'!P16),IF('Nightshift monthly assumed fore'!E12="","",'Nightshift monthly assumed fore'!E12))="",0,IF(DATE(2027,3,1)=DATE(2026,11,1),IF('Model inputs'!P16="","",'Model inputs'!P16),IF('Nightshift monthly assumed fore'!E12="","",'Nightshift monthly assumed fore'!E12)))+'Nightshift monthly assumed fore'!F11 -> 3783 | G12: =IF(IF(DATE(2027,4,1)=DATE(2026,11,1),IF('Model inputs'!P16="","",'Model inputs'!P16),IF('Nightshift monthly assumed fore'!F12="","",'Nightshift monthly assumed fore'!F12))="",0,IF(DATE(2027,4,1)=DATE(2026,11,1),IF('Model inputs'!P16="","",'Model inputs'!P16),IF('Nightshift monthly assumed fore'!F12="","",'Nightshift monthly assumed fore'!F12)))+'Nightshift monthly assumed fore'!G11 -> 4735 | H12: =IF(IF(DATE(2027,5,1)=DATE(2026,11,1),IF('Model inputs'!P16="","",'Model inputs'!P16),IF('Nightshift monthly assumed fore'!G12="","",'Nightshift monthly assumed fore'!G12))="",0,IF(DATE(2027,5,1)=DATE(2026,11,1),IF('Model inputs'!P16="","",'Model inputs'!P16),IF('Nightshift monthly assumed fore'!G12="","",'Nightshift monthly assumed fore'!G12)))+'Nightshift monthly assumed fore'!H11 -> 5687 | I12: =IF(IF(DATE(2027,6,1)=DATE(2026,11,1),IF('Model inputs'!P16="","",'Model inputs'!P16),IF('Nightshift monthly assumed fore'!H12="","",'Nightshift monthly assumed fore'!H12))="",0,IF(DATE(2027,6,1)=DATE(2026,11,1),IF('Model inputs'!P16="","",'Model inputs'!P16),IF('Nightshift monthly assumed fore'!H12="","",'Nightshift monthly assumed fore'!H12)))+'Nightshift monthly assumed fore'!I11 -> 6639 | J12: =IF(IF(DATE(2027,7,1)=DATE(2026,11,1),IF('Model inputs'!P16="","",'Model inputs'!P16),IF('Nightshift monthly assumed fore'!I12="","",'Nightshift monthly assumed fore'!I12))="",0,IF(DATE(2027,7,1)=DATE(2026,11,1),IF('Model inputs'!P16="","",'Model inputs'!P16),IF('Nightshift monthly assumed fore'!I12="","",'Nightshift monthly assumed fore'!I12)))+'Nightshift monthly assumed fore'!J11 -> 7591 | K12: =IF(IF(DATE(2027,8,1)=DATE(2026,11,1),IF('Model inputs'!P16="","",'Model inputs'!P16),IF('Nightshift monthly assumed fore'!J12="","",'Nightshift monthly assumed fore'!J12))="",0,IF(DATE(2027,8,1)=DATE(2026,11,1),IF('Model inputs'!P16="","",'Model inputs'!P16),IF('Nightshift monthly assumed fore'!J12="","",'Nightshift monthly assumed fore'!J12)))+'Nightshift monthly assumed fore'!K11 -> 8543 | L12: =IF(IF(DATE(2027,9,1)=DATE(2026,11,1),IF('Model inputs'!P16="","",'Model inputs'!P16),IF('Nightshift monthly assumed fore'!K12="","",'Nightshift monthly assumed fore'!K12))="",0,IF(DATE(2027,9,1)=DATE(2026,11,1),IF('Model inputs'!P16="","",'Model inputs'!P16),IF('Nightshift monthly assumed fore'!K12="","",'Nightshift monthly assumed fore'!K12)))+'Nightshift monthly assumed fore'!L11 -> 9495 | M12: =IF(IF(DATE(2027,10,1)=DATE(2026,11,1),IF('Model inputs'!P16="","",'Model inputs'!P16),IF('Nightshift monthly assumed fore'!L12="","",'Nightshift monthly assumed fore'!L12))="",0,IF(DATE(2027,10,1)=DATE(2026,11,1),IF('Model inputs'!P16="","",'Model inputs'!P16),IF('Nightshift monthly assumed fore'!L12="","",'Nightshift monthly assumed fore'!L12)))+'Nightshift monthly assumed fore'!M11 -> 10447

Sheet Model inputs
A1: Model inputs
A2: Integration values are aggregated snapshots; raw source records are not included.
A4: Variables
A5: Variable / segment | B5: 2026-09 | C5: 2026-10 | D5: 2026-11 | E5: 2026-12 | F5: 2027-01 | G5: 2027-02 | H5: 2027-03 | I5: 2027-04 | J5: 2027-05 | K5: 2027-06 | L5: 2027-07 | M5: 2027-08 | N5: 2027-09 | O5: 2027-10 | P5: Value
A6: Assumed ending cash | B6: 0 | C6: =IF(IF(DATE(2026,10,1)=DATE(2026,11,1),IF('Model inputs'!P16="","",'Model inputs'!P16),IF('Model inputs'!B6="","",'Model inputs'!B6))="",0,IF(DATE(2026,10,1)=DATE(2026,11,1),IF('Model inputs'!P16="","",'Model inputs'!P16),IF('Model inputs'!B6="","",'Model inputs'!B6)))+'Model inputs'!C11 -> -25 | D6: =IF(IF(DATE(2026,11,1)=DATE(2026,11,1),IF('Model inputs'!P16="","",'Model inputs'!P16),IF('Model inputs'!C6="","",'Model inputs'!C6))="",0,IF(DATE(2026,11,1)=DATE(2026,11,1),IF('Model inputs'!P16="","",'Model inputs'!P16),IF('Model inputs'!C6="","",'Model inputs'!C6)))+'Model inputs'!D11 -> -25 | E6: =IF(IF(DATE(2026,12,1)=DATE(2026,11,1),IF('Model inputs'!P16="","",'Model inputs'!P16),IF('Model inputs'!D6="","",'Model inputs'!D6))="",0,IF(DATE(2026,12,1)=DATE(2026,11,1),IF('Model inputs'!P16="","",'Model inputs'!P16),IF('Model inputs'!D6="","",'Model inputs'!D6)))+'Model inputs'!E11 -> 927 | F6: =IF(IF(DATE(2027,1,1)=DATE(2026,11,1),IF('Model inputs'!P16="","",'Model inputs'!P16),IF('Model inputs'!E6="","",'Model inputs'!E6))="",0,IF(DATE(2027,1,1)=DATE(2026,11,1),IF('Model inputs'!P16="","",'Model inputs'!P16),IF('Model inputs'!E6="","",'Model inputs'!E6)))+'Model inputs'!F11 -> 1879 | G6: =IF(IF(DATE(2027,2,1)=DATE(2026,11,1),IF('Model inputs'!P16="","",'Model inputs'!P16),IF('Model inputs'!F6="","",'Model inputs'!F6))="",0,IF(DATE(2027,2,1)=DATE(2026,11,1),IF('Model inputs'!P16="","",'Model inputs'!P16),IF('Model inputs'!F6="","",'Model inputs'!F6)))+'Model inputs'!G11 -> 2831 | H6: =IF(IF(DATE(2027,3,1)=DATE(2026,11,1),IF('Model inputs'!P16="","",'Model inputs'!P16),IF('Model inputs'!G6="","",'Model inputs'!G6))="",0,IF(DATE(2027,3,1)=DATE(2026,11,1),IF('Model inputs'!P16="","",'Model inputs'!P16),IF('Model inputs'!G6="","",'Model inputs'!G6)))+'Model inputs'!H11 -> 3783 | I6: =IF(IF(DATE(2027,4,1)=DATE(2026,11,1),IF('Model inputs'!P16="","",'Model inputs'!P16),IF('Model inputs'!H6="","",'Model inputs'!H6))="",0,IF(DATE(2027,4,1)=DATE(2026,11,1),IF('Model inputs'!P16="","",'Model inputs'!P16),IF('Model inputs'!H6="","",'Model inputs'!H6)))+'Model inputs'!I11 -> 4735 | J6: =IF(IF(DATE(2027,5,1)=DATE(2026,11,1),IF('Model inputs'!P16="","",'Model inputs'!P16),IF('Model inputs'!I6="","",'Model inputs'!I6))="",0,IF(DATE(2027,5,1)=DATE(2026,11,1),IF('Model inputs'!P16="","",'Model inputs'!P16),IF('Model inputs'!I6="","",'Model inputs'!I6)))+'Model inputs'!J11 -> 5687 | K6: =IF(IF(DATE(2027,6,1)=DATE(2026,11,1),IF('Model inputs'!P16="","",'Model inputs'!P16),IF('Model inputs'!J6="","",'Model inputs'!J6))="",0,IF(DATE(2027,6,1)=DATE(2026,11,1),IF('Model inputs'!P16="","",'Model inputs'!P16),IF('Model inputs'!J6="","",'Model inputs'!J6)))+'Model inputs'!K11 -> 6639 | L6: =IF(IF(DATE(2027,7,1)=DATE(2026,11,1),IF('Model inputs'!P16="","",'Model inputs'!P16),IF('Model inputs'!K6="","",'Model inputs'!K6))="",0,IF(DATE(2027,7,1)=DATE(2026,11,1),IF('Model inputs'!P16="","",'Model inputs'!P16),IF('Model inputs'!K6="","",'Model inputs'!K6)))+'Model inputs'!L11 -> 7591 | M6: =IF(IF(DATE(2027,8,1)=DATE(2026,11,1),IF('Model inputs'!P16="","",'Model inputs'!P16),IF('Model inputs'!L6="","",'Model inputs'!L6))="",0,IF(DATE(2027,8,1)=DATE(2026,11,1),IF('Model inputs'!P16="","",'Model inputs'!P16),IF('Model inputs'!L6="","",'Model inputs'!L6)))+'Model inputs'!M11 -> 8543 | N6: =IF(IF(DATE(2027,9,1)=DATE(2026,11,1),IF('Model inputs'!P16="","",'Model inputs'!P16),IF('Model inputs'!M6="","",'Model inputs'!M6))="",0,IF(DATE(2027,9,1)=DATE(2026,11,1),IF('Model inputs'!P16="","",'Model inputs'!P16),IF('Model inputs'!M6="","",'Model inputs'!M6)))+'Model inputs'!N11 -> 9495 | O6: =IF(IF(DATE(2027,10,1)=DATE(2026,11,1),IF('Model inputs'!P16="","",'Model inputs'!P16),IF('Model inputs'!N6="","",'Model inputs'!N6))="",0,IF(DATE(2027,10,1)=DATE(2026,11,1),IF('Model inputs'!P16="","",'Model inputs'!P16),IF('Model inputs'!N6="","",'Model inputs'!N6)))+'Model inputs'!O11 -> 10447
A7: Assumed infrastructure | B7: 0 | C7: =IF('Model inputs'!P10="","",'Model inputs'!P10) -> 25 | D7: =IF('Model inputs'!P10="","",'Model inputs'!P10) -> 25 | E7: =IF('Model inputs'!P10="","",'Model inputs'!P10) -> 25 | F7: =IF('Model inputs'!P10="","",'Model inputs'!P10) -> 25 | G7: =IF('Model inputs'!P10="","",'Model inputs'!P10) -> 25 | H7: =IF('Model inputs'!P10="","",'Model inputs'!P10) -> 25 | I7: =IF('Model inputs'!P10="","",'Model inputs'!P10) -> 25 | J7: =IF('Model inputs'!P10="","",'Model inputs'!P10) -> 25 | K7: =IF('Model inputs'!P10="","",'Model inputs'!P10) -> 25 | L7: =IF('Model inputs'!P10="","",'Model inputs'!P10) -> 25 | M7: =IF('Model inputs'!P10="","",'Model inputs'!P10) -> 25 | N7: =IF('Model inputs'!P10="","",'Model inputs'!P10) -> 25 | O7: =IF('Model inputs'!P10="","",'Model inputs'!P10) -> 25
A8: Assumed model cost | B8: 0 | C8: ='Model inputs'!P9*'Model inputs'!C12 -> 0 | D8: ='Model inputs'!P9*'Model inputs'!D12 -> 0 | E8: ='Model inputs'!P9*'Model inputs'!E12 -> 3 | F8: ='Model inputs'!P9*'Model inputs'!F12 -> 3 | G8: ='Model inputs'!P9*'Model inputs'!G12 -> 3 | H8: ='Model inputs'!P9*'Model inputs'!H12 -> 3 | I8: ='Model inputs'!P9*'Model inputs'!I12 -> 3 | J8: ='Model inputs'!P9*'Model inputs'!J12 -> 3 | K8: ='Model inputs'!P9*'Model inputs'!K12 -> 3 | L8: ='Model inputs'!P9*'Model inputs'!L12 -> 3 | M8: ='Model inputs'!P9*'Model inputs'!M12 -> 3 | N8: ='Model inputs'!P9*'Model inputs'!N12 -> 3 | O8: ='Model inputs'!P9*'Model inputs'!O12 -> 3
A9: Assumed model cost per run | P9: =0.15 -> 0.15
A10: Assumed monthly infrastructure input | P10: =25 -> 25
A11: Assumed operating result | B11: 0 | C11: ='Model inputs'!C15-'Model inputs'!C17 -> -25 | D11: ='Model inputs'!D15-'Model inputs'!D17 -> -25 | E11: ='Model inputs'!E15-'Model inputs'!E17 -> 952 | F11: ='Model inputs'!F15-'Model inputs'!F17 -> 952 | G11: ='Model inputs'!G15-'Model inputs'!G17 -> 952 | H11: ='Model inputs'!H15-'Model inputs'!H17 -> 952 | I11: ='Model inputs'!I15-'Model inputs'!I17 -> 952 | J11: ='Model inputs'!J15-'Model inputs'!J17 -> 952 | ... O11: ='Model inputs'!O15-'Model inputs'!O17 -> 952
A12: Assumed paid runs | B12: 0 | C12: 0 | D12: ='Nightshift monthly assumed fore'!B6 -> 0 | E12: ='Nightshift monthly assumed fore'!C6 -> 20 | F12: ='Nightshift monthly assumed fore'!D6 -> 20 | G12: ='Nightshift monthly assumed fore'!E6 -> 20 | H12: ='Nightshift monthly assumed fore'!F6 -> 20 | I12: ='Nightshift monthly assumed fore'!G6 -> 20 | J12: ='Nightshift monthly assumed fore'!H6 -> 20 | K12: ='Nightshift monthly assumed fore'!I6 -> 20 | ... O12: ='Nightshift monthly assumed fore'!M6 -> 20
A13: Assumed price | B13: =IF('Model inputs'!P14="","",'Model inputs'!P14) -> 49 | C13: =IF('Model inputs'!P14="","",'Model inputs'!P14) -> 49 | D13: =IF('Model inputs'!P14="","",'Model inputs'!P14) -> 49 | E13: =IF('Model inputs'!P14="","",'Model inputs'!P14) -> 49 | F13: =IF('Model inputs'!P14="","",'Model inputs'!P14) -> 49 | G13: =IF('Model inputs'!P14="","",'Model inputs'!P14) -> 49 | H13: =IF('Model inputs'!P14="","",'Model inputs'!P14) -> 49 | I13: =IF('Model inputs'!P14="","",'Model inputs'!P14) -> 49 | J13: =IF('Model inputs'!P14="","",'Model inputs'!P14) -> 49 | K13: =IF('Model inputs'!P14="","",'Model inputs'!P14) -> 49 | L13: =IF('Model inputs'!P14="","",'Model inputs'!P14) -> 49 | M13: =IF('Model inputs'!P14="","",'Model inputs'!P14) -> 49 | N13: =IF('Model inputs'!P14="","",'Model inputs'!P14) -> 49 | O13: =IF('Model inputs'!P14="","",'Model inputs'!P14) -> 49
A14: Assumed recovery price | P14: =49 -> 49
A15: Assumed revenue | B15: 0 | C15: ='Model inputs'!C13*'Model inputs'!C12 -> 0 | D15: ='Model inputs'!D13*'Model inputs'!D12 -> 0 | E15: ='Model inputs'!E13*'Model inputs'!E12 -> 980 | F15: ='Model inputs'!F13*'Model inputs'!F12 -> 980 | G15: ='Model inputs'!G13*'Model inputs'!G12 -> 980 | H15: ='Model inputs'!H13*'Model inputs'!H12 -> 980 | I15: ='Model inputs'!I13*'Model inputs'!I12 -> 980 | J15: ='Model inputs'!J13*'Model inputs'!J12 -> 980 | ... O15: ='Model inputs'!O13*'Model inputs'!O12 -> 980
A16: Assumed starting cash | P16: =0 -> 0
A17: Assumed total cost | B17: 0 | C17: ='Model inputs'!C8+'Model inputs'!C7 -> 25 | D17: ='Model inputs'!D8+'Model inputs'!D7 -> 25 | E17: ='Model inputs'!E8+'Model inputs'!E7 -> 28 | F17: ='Model inputs'!F8+'Model inputs'!F7 -> 28 | G17: ='Model inputs'!G8+'Model inputs'!G7 -> 28 | H17: ='Model inputs'!H8+'Model inputs'!H7 -> 28 | I17: ='Model inputs'!I8+'Model inputs'!I7 -> 28 | J17: ='Model inputs'!J8+'Model inputs'!J7 -> 28 | ... O17: ='Model inputs'!O8+'Model inputs'!O7 -> 28
